[{"income_type":"asdjfkl;","message":"asdfjkl;","value":234.0}
,{"income_type":"asdjfkl;","message":"asdjfkl;","value":234.0}
,{"income_type":"asdjfkl;","message":"asdjfkl;","value":234.0}
,{"income_type":"asdjfkl;","message":"asdjfkl;","value":234.0}
,{"income_type":"asdjfkl;","message":"asdjfkl;","value":234.0}
,{"income_type":"asdjfkl;","message":"asdjfkl;","value":234.0}
,{"income_type":"asdjfkl;","message":"asdjfkl;","value":234.0}
,{"income_type":"asdjfkl;","message":"asdjfkl;asdf","value":234.0}
,{"income_type":"asdjfkl;","message":"asdjfkl;asdf","value":234.0}]